<?xml version="1.0" encoding="utf-8"?>
<Data xmlns:xsi="http://www.w3.org/2001/XMLSchema-instance" xmlns:xsd="http://www.w3.org/2001/XMLSchema">
  <Record>
    <Id>sample.purchase_order_order_1</Id>
    <Name>PO00001</Name>
    <PartnerId>sample.partner_supplier_1</PartnerId>
    <PickingTypeId>stock.stock_picking_type_incoming</PickingTypeId>
    <AmountTotal>185000.00</AmountTotal>
    <JournalId>account.data_account_journal_cash</JournalId>
    <DateRound>-12</DateRound>
    <OrderLines>
      <Record>
        <ProductQty>1.00</ProductQty>
        <ProductUOMId>product.product_uom_unit</ProductUOMId>
        <ProductId>sample.product_product_56</ProductId>
        <PriceSubtotal>35000.00</PriceSubtotal>
        <PriceTotal>35000.00</PriceTotal>
        <PartnerId>sample.partner_supplier_1</PartnerId>
        <PriceUnit>35000.00</PriceUnit>
      </Record>
      <Record>
        <ProductQty>1.00</ProductQty>
        <ProductUOMId>product.product_uom_unit</ProductUOMId>
        <ProductId>sample.product_product_57</ProductId>
        <PriceSubtotal>98000.00</PriceSubtotal>
        <PriceTotal>98000.00</PriceTotal>
        <PartnerId>sample.partner_supplier_1</PartnerId>
        <PriceUnit>98000.00</PriceUnit>
      </Record>
      <Record>
        <ProductQty>1.00</ProductQty>
        <ProductUOMId>product.product_uom_unit</ProductUOMId>
        <ProductId>sample.product_product_19</ProductId>
        <PriceSubtotal>32000.00</PriceSubtotal>
        <PriceTotal>32000.00</PriceTotal>
        <PartnerId>sample.partner_supplier_1</PartnerId>
        <PriceUnit>32000.00</PriceUnit>
      </Record>
      <Record>
        <ProductQty>1.00</ProductQty>
        <ProductUOMId>product.product_uom_unit</ProductUOMId>
        <ProductId>sample.product_product_20</ProductId>
        <PriceSubtotal>20000.00</PriceSubtotal>
        <PriceTotal>20000.00</PriceTotal>
        <PartnerId>sample.partner_supplier_1</PartnerId>
        <PriceUnit>20000.00</PriceUnit>
      </Record>
    </OrderLines>
  </Record>
</Data>